{
    "projects":[
        {
            "id":1,
            "name": "BMI",
            "image": "https://i.postimg.cc/cHN1qfSZ/bmi-formula.jpg",
            "github": "https://github.com/sisiphopeps/bmi-calculator.git",
            "netlify": "https://bmi-calculator-sisipho.netlify.app"
        },
        {
            "id":2,
            "name": "Temperature Converter",
            "image": "https://i.postimg.cc/CMnyCRTs/download-1.png",
            "github": "https://github.com/sisiphopeps/convertor.git",
            "netlify": "https://temp-converter-sisipho.netlify.app"
        },
        {
            "id":3,
            "name": "E-commerce",
            "image": "https://i.postimg.cc/X7nTRQBQ/mehloperfume.png",
            "github": "https://github.com/sisiphopeps/EOMP-JS.git",
            "netlify": "https://spontaneous-banoffee-4f4acd.netlify.app"
        },
        {
            "id":4,
            "name": "Bookshop",
            "image": "https://i.postimg.cc/90GkqqRm/The-Paperback-Bruncher-Putting-the-Lover-in-Book-Lovers-2.jpg",
            "github": "https://github.com/sisiphopeps/bookshop.git",
            "netlify": "https://bookshop-sisipho.netlify.app"
        },
        {
            "id":5,
            "name": "Portfolio",
            "image": "https://i.postimg.cc/fyJxG4s6/How-to-make-portfolio-for-design-admission.jpg",
            "github": "https://github.com/sisiphopeps/HTML-CSS_PROJECT.git",
            "netlify": "https://html-css-bootstrap-project.netlify.app"
        },
        {
            "id":6,
            "name": "To Do List",
            "image": "https://i.postimg.cc/9QzvL0sp/rm252batch3-ning-instagramstory-01-1-2.jpg",
            "github": "https://github.com/sisiphopeps/to-do-list.git",
            "netlify": "https://verdant-chebakia-5ed5fa.netlify.app"
        }
    ]

}